agent_environment/__init__.py
agent_environment/environment.py
agent_environment/exceptions.py
agent_environment/file_operator.py
agent_environment/protocols.py
agent_environment/resources.py
agent_environment/shell.py
agent_environment/types.py
agent_environment/utils.py
agent_environment-0.4.0.dist-info/METADATA
agent_environment-0.4.0.dist-info/WHEEL
agent_environment-0.4.0.dist-info/licenses/LICENSE
agent_environment-0.4.0.dist-info/RECORD
